setup.py
dm/__init__.py
dm.zope.rpc_protocol.wsdl_suds.egg-info/PKG-INFO
dm.zope.rpc_protocol.wsdl_suds.egg-info/SOURCES.txt
dm.zope.rpc_protocol.wsdl_suds.egg-info/dependency_links.txt
dm.zope.rpc_protocol.wsdl_suds.egg-info/namespace_packages.txt
dm.zope.rpc_protocol.wsdl_suds.egg-info/not-zip-safe
dm.zope.rpc_protocol.wsdl_suds.egg-info/requires.txt
dm.zope.rpc_protocol.wsdl_suds.egg-info/top_level.txt
dm/zope/__init__.py
dm/zope/rpc_protocol/__init__.py
dm/zope/rpc_protocol/wsdl_suds/LICENSE.txt
dm/zope/rpc_protocol/wsdl_suds/README.txt
dm/zope/rpc_protocol/wsdl_suds/VERSION.txt
dm/zope/rpc_protocol/wsdl_suds/__init__.py
dm/zope/rpc_protocol/wsdl_suds/tests/__init__.py
dm/zope/rpc_protocol/wsdl_suds/tests/soap/__init__.py
dm/zope/rpc_protocol/wsdl_suds/tests/soap/configure.zcml
dm/zope/rpc_protocol/wsdl_suds/tests/soap/browser/__init__.py
dm/zope/rpc_protocol/wsdl_suds/tests/soap/browser/configure.zcml
dm/zope/rpc_protocol/wsdl_suds/tests/soap/browser/service.py
dm/zope/rpc_protocol/wsdl_suds/tests/soap/browser/service.wsdl
dm/zope/rpc_protocol/wsdl_suds/tests/soap/browser/soap.py